LICENSE
README.md
setup.py
serial_for_controller/SerialPi.py
serial_for_controller/__init__.py
serial_for_controller/serial_aaarch64.so
serial_for_controller/serial_armv71.so
serial_for_controller.egg-info/PKG-INFO
serial_for_controller.egg-info/SOURCES.txt
serial_for_controller.egg-info/dependency_links.txt
serial_for_controller.egg-info/requires.txt
serial_for_controller.egg-info/top_level.txt